MANIFEST.in
README.rst
setup.cfg
setup.py
bin/pfurl
pfurl/__init__.py
pfurl/pfurl.py
pfurl.egg-info/PKG-INFO
pfurl.egg-info/SOURCES.txt
pfurl.egg-info/dependency_links.txt
pfurl.egg-info/not-zip-safe
pfurl.egg-info/requires.txt
pfurl.egg-info/top_level.txt