Metadata-Version: 1.0
Name: pfurl
Version: 2.3.0.1
Summary: (Python) Path-File URL comms
Home-page: https://github.com/FNNDSC/pfurl
Author: Rudolph Pienaar
Author-email: rudolph.pienaar@gmail.com
License: MIT
Platform: UNKNOWN
